py_progress/__init__.py
py_progress-0.1.dist-info/LICENSE
py_progress-0.1.dist-info/METADATA
py_progress-0.1.dist-info/WHEEL
py_progress-0.1.dist-info/top_level.txt
py_progress-0.1.dist-info/RECORD
